chatgpt/__init__.py
chatgpt/consts.py
chatgpt_serpucga-0.0.3.dist-info/METADATA
chatgpt_serpucga-0.0.3.dist-info/WHEEL
chatgpt_serpucga-0.0.3.dist-info/top_level.txt
chatgpt_serpucga-0.0.3.dist-info/RECORD
