Metadata-Version: 2.1
Name: chatgpt-serpucga
Version: 0.0.3
Summary: Client library to communicate with the ChatGPT API
Home-page: https://gitlab.com/Serbaf/chatgpt_client
Author: Sergio Puche García
Author-email: spuche@upv.es
License: GPL3
